[{"pose": [{"indices": 0, "x": 0.0, "y": 0.0, "visibility": 0.0}, {"indices": 1, "x": 0.0, "y": 0.0, "visibility": 0.0}, {"indices": 2, "x": 0.0, "y": 0.0, "visibility": 0.0}, {"indices": 3, "x": 0.0, "y": 0.0, "visibility": 0.0}, {"indices": 4, "x": 0.0, "y": 0.0, "visibility": 0.0}, {"indices": 5, "x": 0.0, "y": 0.0, "visibility": 0.0}, {"indices": 6, "x": 0.0, "y": 0.0, "visibility": 0.0}, {"indices": 7, "x": 0.0, "y": 0.0, "visibility": 0.0}, {"indices": 8, "x": 0.0, "y": 0.0, "visibility": 0.0}, {"indices": 9, "x": 0.0, "y": 0.0, "visibility": 0.0}, {"indices": 10, "x": 0.0, "y": 0.0, "visibility": 0.0}, {"indices": 11, "x": 0.0, "y": 0.0, "visibility": 0.0}, {"indices": 12, "x": 0.0, "y": 0.0, "visibility": 0.0}, {"indices": 13, "x": 0.0, "y": 0.0, "visibility": 0.0}, {"indices": 14, "x": 0.0, "y": 0.0, "visibility": 0.0}, {"indices": 15, "x": 0.0, "y": 0.0, "visibility": 0.0}, {"indices": 16, "x": 0.0, "y": 0.0, "visibility": 0.0}, {"indices": 23, "x": 0.0, "y": 0.0, "visibility": 0.0}, {"indices": 24, "x": 0.0, "y": 0.0, "visibility": 0.0}], "left_hand": [{"indices": 0, "x": 0.0, "y": 0.0, "visibility": 0.0}, {"indices": 1, "x": 0.0, "y": 0.0, "visibility": 0.0}, {"indices": 2, "x": 0.0, "y": 0.0, "visibility": 0.0}, {"indices": 3, "x": 0.0, "y": 0.0, "visibility": 0.0}, {"indices": 4, "x": 0.0, "y": 0.0, "visibility": 0.0}, {"indices": 5, "x": 0.0, "y": 0.0, "visibility": 0.0}, {"indices": 6, "x": 0.0, "y": 0.0, "visibility": 0.0}, {"indices": 7, "x": 0.0, "y": 0.0, "visibility": 0.0}, {"indices": 8, "x": 0.0, "y": 0.0, "visibility": 0.0}, {"indices": 9, "x": 0.0, "y": 0.0, "visibility": 0.0}, {"indices": 10, "x": 0.0, "y": 0.0, "visibility": 0.0}, {"indices": 11, "x": 0.0, "y": 0.0, "visibility": 0.0}, {"indices": 12, "x": 0.0, "y": 0.0, "visibility": 0.0}, {"indices": 13, "x": 0.0, "y": 0.0, "visibility": 0.0}, {"indices": 14, "x": 0.0, "y": 0.0, "visibility": 0.0}, {"indices": 15, "x": 0.0, "y": 0.0, "visibility": 0.0}, {"indices": 16, "x": 0.0, "y": 0.0, "visibility": 0.0}, {"indices": 17, "x": 0.0, "y": 0.0, "visibility": 0.0}, {"indices": 18, "x": 0.0, "y": 0.0, "visibility": 0.0}, {"indices": 19, "x": 0.0, "y": 0.0, "visibility": 0.0}, {"indices": 20, "x": 0.0, "y": 0.0, "visibility": 0.0}], "right_hand": [{"indices": 0, "x": 0.11153254052209081, "y": 0.5636595085927096, "visibility": 1.0}, {"indices": 1, "x": 0.23177786050561563, "y": 0.607829834272494, "visibility": 1.0}, {"indices": 2, "x": 0.3396584989299342, "y": 0.5788323341501167, "visibility": 1.0}, {"indices": 3, "x": 0.41153001401504913, "y": 0.5179154004473785, "visibility": 1.0}, {"indices": 4, "x": 0.4497641870243816, "y": 0.47467825882336473, "visibility": 1.0}, {"indices": 5, "x": 0.39870277010292315, "y": 0.5638065647584493, "visibility": 1.0}, {"indices": 6, "x": 0.5333388037258335, "y": 0.5212742189942066, "visibility": 1.0}, {"indices": 7, "x": 0.6034005714011982, "y": 0.49946515249780615, "visibility": 1.0}, {"indices": 8, "x": 0.6560286152772556, "y": 0.48081398707934186, "visibility": 1.0}, {"indices": 9, "x": 0.3753957228597998, "y": 0.48774678593738946, "visibility": 1.0}, {"indices": 10, "x": 0.5187493796076859, "y": 0.4366543673152065, "visibility": 1.0}, {"indices": 11, "x": 0.5908648448492607, "y": 0.406386067768086, "visibility": 1.0}, {"indices": 12, "x": 0.6478681746231633, "y": 0.38635830357903994, "visibility": 1.0}, {"indices": 13, "x": 0.34004964921662156, "y": 0.4132917694305651, "visibility": 1.0}, {"indices": 14, "x": 0.472404482611653, "y": 0.37126824900838856, "visibility": 1.0}, {"indices": 15, "x": 0.5408157963842417, "y": 0.35280986749155074, "visibility": 1.0}, {"indices": 16, "x": 0.5991363989834633, "y": 0.33183935104450335, "visibility": 1.0}, {"indices": 17, "x": 0.2833932141136722, "y": 0.3593124217971209, "visibility": 1.0}, {"indices": 18, "x": 0.3869952032401965, "y": 0.3377610121893476, "visibility": 1.0}, {"indices": 19, "x": 0.38695990167232547, "y": 0.3582420063355124, "visibility": 1.0}, {"indices": 20, "x": 0.37002724265873244, "y": 0.3754895854047024, "visibility": 1.0}]}, {"pose": [{"indices": 0, "x": 0.0, "y": 0.0, "visibility": 0.0}, {"indices": 1, "x": 0.0, "y": 0.0, "visibility": 0.0}, {"indices": 2, "x": 0.0, "y": 0.0, "visibility": 0.0}, {"indices": 3, "x": 0.0, "y": 0.0, "visibility": 0.0}, {"indices": 4, "x": 0.0, "y": 0.0, "visibility": 0.0}, {"indices": 5, "x": 0.0, "y": 0.0, "visibility": 0.0}, {"indices": 6, "x": 0.0, "y": 0.0, "visibility": 0.0}, {"indices": 7, "x": 0.0, "y": 0.0, "visibility": 0.0}, {"indices": 8, "x": 0.0, "y": 0.0, "visibility": 0.0}, {"indices": 9, "x": 0.0, "y": 0.0, "visibility": 0.0}, {"indices": 10, "x": 0.0, "y": 0.0, "visibility": 0.0}, {"indices": 11, "x": 0.0, "y": 0.0, "visibility": 0.0}, {"indices": 12, "x": 0.0, "y": 0.0, "visibility": 0.0}, {"indices": 13, "x": 0.0, "y": 0.0, "visibility": 0.0}, {"indices": 14, "x": 0.0, "y": 0.0, "visibility": 0.0}, {"indices": 15, "x": 0.0, "y": 0.0, "visibility": 0.0}, {"indices": 16, "x": 0.0, "y": 0.0, "visibility": 0.0}, {"indices": 23, "x": 0.0, "y": 0.0, "visibility": 0.0}, {"indices": 24, "x": 0.0, "y": 0.0, "visibility": 0.0}], "left_hand": [{"indices": 0, "x": 0.0, "y": 0.0, "visibility": 0.0}, {"indices": 1, "x": 0.0, "y": 0.0, "visibility": 0.0}, {"indices": 2, "x": 0.0, "y": 0.0, "visibility": 0.0}, {"indices": 3, "x": 0.0, "y": 0.0, "visibility": 0.0}, {"indices": 4, "x": 0.0, "y": 0.0, "visibility": 0.0}, {"indices": 5, "x": 0.0, "y": 0.0, "visibility": 0.0}, {"indices": 6, "x": 0.0, "y": 0.0, "visibility": 0.0}, {"indices": 7, "x": 0.0, "y": 0.0, "visibility": 0.0}, {"indices": 8, "x": 0.0, "y": 0.0, "visibility": 0.0}, {"indices": 9, "x": 0.0, "y": 0.0, "visibility": 0.0}, {"indices": 10, "x": 0.0, "y": 0.0, "visibility": 0.0}, {"indices": 11, "x": 0.0, "y": 0.0, "visibility": 0.0}, {"indices": 12, "x": 0.0, "y": 0.0, "visibility": 0.0}, {"indices": 13, "x": 0.0, "y": 0.0, "visibility": 0.0}, {"indices": 14, "x": 0.0, "y": 0.0, "visibility": 0.0}, {"indices": 15, "x": 0.0, "y": 0.0, "visibility": 0.0}, {"indices": 16, "x": 0.0, "y": 0.0, "visibility": 0.0}, {"indices": 17, "x": 0.0, "y": 0.0, "visibility": 0.0}, {"indices": 18, "x": 0.0, "y": 0.0, "visibility": 0.0}, {"indices": 19, "x": 0.0, "y": 0.0, "visibility": 0.0}, {"indices": 20, "x": 0.0, "y": 0.0, "visibility": 0.0}], "right_hand": [{"indices": 0, "x": 0.11129663504892952, "y": 0.5645378625961912, "visibility": 1.0}, {"indices": 1, "x": 0.2310848626923491, "y": 0.6049693079510604, "visibility": 1.0}, {"indices": 2, "x": 0.3412424933201325, "y": 0.5793026983848298, "visibility": 1.0}, {"indices": 3, "x": 0.4101145067782465, "y": 0.5190662635177006, "visibility": 1.0}, {"indices": 4, "x": 0.450169918007484, "y": 0.4730904706733158, "visibility": 1.0}, {"indices": 5, "x": 0.39691111921298305, "y": 0.5642807309427583, "visibility": 1.0}, {"indices": 6, "x": 0.532202264500656, "y": 0.5242770503199785, "visibility": 1.0}, {"indices": 7, "x": 0.6004676334692186, "y": 0.49895009601197926, "visibility": 1.0}, {"indices": 8, "x": 0.6578430107326382, "y": 0.48194944253272287, "visibility": 1.0}, {"indices": 9, "x": 0.37761190698901703, "y": 0.48477429717691234, "visibility": 1.0}, {"indices": 10, "x": 0.5178595713680016, "y": 0.43701595290991924, "visibility": 1.0}, {"indices": 11, "x": 0.5908684881165025, "y": 0.4068789199303633, "visibility": 1.0}, {"indices": 12, "x": 0.6475429166777289, "y": 0.38428294142029157, "visibility": 1.0}, {"indices": 13, "x": 0.3396246000464815, "y": 0.4160888351073255, "visibility": 1.0}, {"indices": 14, "x": 0.4711024475786782, "y": 0.3712965706351749, "visibility": 1.0}, {"indices": 15, "x": 0.5435621334754395, "y": 0.3519820560952282, "visibility": 1.0}, {"indices": 16, "x": 0.5956821855123924, "y": 0.3347890624494978, "visibility": 1.0}, {"indices": 17, "x": 0.2857269746842575, "y": 0.35918872556230885, "visibility": 1.0}, {"indices": 18, "x": 0.38842181493294214, "y": 0.337088481402131, "visibility": 1.0}, {"indices": 19, "x": 0.387349943553111, "y": 0.3573548070576655, "visibility": 1.0}, {"indices": 20, "x": 0.37156940657361065, "y": 0.3776001976213064, "visibility": 1.0}]}, {"pose": [{"indices": 0, "x": 0.0, "y": 0.0, "visibility": 0.0}, {"indices": 1, "x": 0.0, "y": 0.0, "visibility": 0.0}, {"indices": 2, "x": 0.0, "y": 0.0, "visibility": 0.0}, {"indices": 3, "x": 0.0, "y": 0.0, "visibility": 0.0}, {"indices": 4, "x": 0.0, "y": 0.0, "visibility": 0.0}, {"indices": 5, "x": 0.0, "y": 0.0, "visibility": 0.0}, {"indices": 6, "x": 0.0, "y": 0.0, "visibility": 0.0}, {"indices": 7, "x": 0.0, "y": 0.0, "visibility": 0.0}, {"indices": 8, "x": 0.0, "y": 0.0, "visibility": 0.0}, {"indices": 9, "x": 0.0, "y": 0.0, "visibility": 0.0}, {"indices": 10, "x": 0.0, "y": 0.0, "visibility": 0.0}, {"indices": 11, "x": 0.0, "y": 0.0, "visibility": 0.0}, {"indices": 12, "x": 0.0, "y": 0.0, "visibility": 0.0}, {"indices": 13, "x": 0.0, "y": 0.0, "visibility": 0.0}, {"indices": 14, "x": 0.0, "y": 0.0, "visibility": 0.0}, {"indices": 15, "x": 0.0, "y": 0.0, "visibility": 0.0}, {"indices": 16, "x": 0.0, "y": 0.0, "visibility": 0.0}, {"indices": 23, "x": 0.0, "y": 0.0, "visibility": 0.0}, {"indices": 24, "x": 0.0, "y": 0.0, "visibility": 0.0}], "left_hand": [{"indices": 0, "x": 0.0, "y": 0.0, "visibility": 0.0}, {"indices": 1, "x": 0.0, "y": 0.0, "visibility": 0.0}, {"indices": 2, "x": 0.0, "y": 0.0, "visibility": 0.0}, {"indices": 3, "x": 0.0, "y": 0.0, "visibility": 0.0}, {"indices": 4, "x": 0.0, "y": 0.0, "visibility": 0.0}, {"indices": 5, "x": 0.0, "y": 0.0, "visibility": 0.0}, {"indices": 6, "x": 0.0, "y": 0.0, "visibility": 0.0}, {"indices": 7, "x": 0.0, "y": 0.0, "visibility": 0.0}, {"indices": 8, "x": 0.0, "y": 0.0, "visibility": 0.0}, {"indices": 9, "x": 0.0, "y": 0.0, "visibility": 0.0}, {"indices": 10, "x": 0.0, "y": 0.0, "visibility": 0.0}, {"indices": 11, "x": 0.0, "y": 0.0, "visibility": 0.0}, {"indices": 12, "x": 0.0, "y": 0.0, "visibility": 0.0}, {"indices": 13, "x": 0.0, "y": 0.0, "visibility": 0.0}, {"indices": 14, "x": 0.0, "y": 0.0, "visibility": 0.0}, {"indices": 15, "x": 0.0, "y": 0.0, "visibility": 0.0}, {"indices": 16, "x": 0.0, "y": 0.0, "visibility": 0.0}, {"indices": 17, "x": 0.0, "y": 0.0, "visibility": 0.0}, {"indices": 18, "x": 0.0, "y": 0.0, "visibility": 0.0}, {"indices": 19, "x": 0.0, "y": 0.0, "visibility": 0.0}, {"indices": 20, "x": 0.0, "y": 0.0, "visibility": 0.0}], "right_hand": [{"indices": 0, "x": 0.11452233581455466, "y": 0.5640608908353013, "visibility": 1.0}, {"indices": 1, "x": 0.23104237874603298, "y": 0.6047710563896272, "visibility": 1.0}, {"indices": 2, "x": 0.33878293338635385, "y": 0.577185988854817, "visibility": 1.0}, {"indices": 3, "x": 0.413677251707377, "y": 0.5199000151687423, "visibility": 1.0}, {"indices": 4, "x": 0.4479322494878657, "y": 0.4740707883905823, "visibility": 1.0}, {"indices": 5, "x": 0.39738124542207176, "y": 0.5638623781306182, "visibility": 1.0}, {"indices": 6, "x": 0.5313626763005361, "y": 0.5216696001636331, "visibility": 1.0}, {"indices": 7, "x": 0.6024272476606276, "y": 0.5013398049714343, "visibility": 1.0}, {"indices": 8, "x": 0.6558378550999996, "y": 0.4801415181925353, "visibility": 1.0}, {"indices": 9, "x": 0.37821821759202434, "y": 0.4867124683512179, "visibility": 1.0}, {"indices": 10, "x": 0.5177661519531654, "y": 0.4365382734484372, "visibility": 1.0}, {"indices": 11, "x": 0.5909303066553996, "y": 0.40881482591162394, "visibility": 1.0}, {"indices": 12, "x": 0.6500186227274468, "y": 0.38414487146847504, "visibility": 1.0}, {"indices": 13, "x": 0.3403102222868163, "y": 0.41472943718911803, "visibility": 1.0}, {"indices": 14, "x": 0.4721794978029803, "y": 0.37401846495965735, "visibility": 1.0}, {"indices": 15, "x": 0.5411051915440083, "y": 0.352218525751814, "visibility": 1.0}, {"indices": 16, "x": 0.5972401690811964, "y": 0.332239640931238, "visibility": 1.0}, {"indices": 17, "x": 0.2845430080621682, "y": 0.35649965997441174, "visibility": 1.0}, {"indices": 18, "x": 0.38874012576180894, "y": 0.33591934265687295, "visibility": 1.0}, {"indices": 19, "x": 0.38571564520370594, "y": 0.3545544398088015, "visibility": 1.0}, {"indices": 20, "x": 0.37228890399828796, "y": 0.37690598385286256, "visibility": 1.0}]}]