[{"pose": [{"indices": 0, "x": 0.0, "y": 0.0, "visibility": 0.0}, {"indices": 1, "x": 0.0, "y": 0.0, "visibility": 0.0}, {"indices": 2, "x": 0.0, "y": 0.0, "visibility": 0.0}, {"indices": 3, "x": 0.0, "y": 0.0, "visibility": 0.0}, {"indices": 4, "x": 0.0, "y": 0.0, "visibility": 0.0}, {"indices": 5, "x": 0.0, "y": 0.0, "visibility": 0.0}, {"indices": 6, "x": 0.0, "y": 0.0, "visibility": 0.0}, {"indices": 7, "x": 0.0, "y": 0.0, "visibility": 0.0}, {"indices": 8, "x": 0.0, "y": 0.0, "visibility": 0.0}, {"indices": 9, "x": 0.0, "y": 0.0, "visibility": 0.0}, {"indices": 10, "x": 0.0, "y": 0.0, "visibility": 0.0}, {"indices": 11, "x": 0.0, "y": 0.0, "visibility": 0.0}, {"indices": 12, "x": 0.0, "y": 0.0, "visibility": 0.0}, {"indices": 13, "x": 0.0, "y": 0.0, "visibility": 0.0}, {"indices": 14, "x": 0.0, "y": 0.0, "visibility": 0.0}, {"indices": 15, "x": 0.0, "y": 0.0, "visibility": 0.0}, {"indices": 16, "x": 0.0, "y": 0.0, "visibility": 0.0}, {"indices": 23, "x": 0.0, "y": 0.0, "visibility": 0.0}, {"indices": 24, "x": 0.0, "y": 0.0, "visibility": 0.0}], "left_hand": [{"indices": 0, "x": 0.0, "y": 0.0, "visibility": 0.0}, {"indices": 1, "x": 0.0, "y": 0.0, "visibility": 0.0}, {"indices": 2, "x": 0.0, "y": 0.0, "visibility": 0.0}, {"indices": 3, "x": 0.0, "y": 0.0, "visibility": 0.0}, {"indices": 4, "x": 0.0, "y": 0.0, "visibility": 0.0}, {"indices": 5, "x": 0.0, "y": 0.0, "visibility": 0.0}, {"indices": 6, "x": 0.0, "y": 0.0, "visibility": 0.0}, {"indices": 7, "x": 0.0, "y": 0.0, "visibility": 0.0}, {"indices": 8, "x": 0.0, "y": 0.0, "visibility": 0.0}, {"indices": 9, "x": 0.0, "y": 0.0, "visibility": 0.0}, {"indices": 10, "x": 0.0, "y": 0.0, "visibility": 0.0}, {"indices": 11, "x": 0.0, "y": 0.0, "visibility": 0.0}, {"indices": 12, "x": 0.0, "y": 0.0, "visibility": 0.0}, {"indices": 13, "x": 0.0, "y": 0.0, "visibility": 0.0}, {"indices": 14, "x": 0.0, "y": 0.0, "visibility": 0.0}, {"indices": 15, "x": 0.0, "y": 0.0, "visibility": 0.0}, {"indices": 16, "x": 0.0, "y": 0.0, "visibility": 0.0}, {"indices": 17, "x": 0.0, "y": 0.0, "visibility": 0.0}, {"indices": 18, "x": 0.0, "y": 0.0, "visibility": 0.0}, {"indices": 19, "x": 0.0, "y": 0.0, "visibility": 0.0}, {"indices": 20, "x": 0.0, "y": 0.0, "visibility": 0.0}], "right_hand": [{"indices": 0, "x": 0.0, "y": 0.0, "visibility": 0.0}, {"indices": 1, "x": 0.9618276598350655, "y": 0.49868544632717005, "visibility": 1.0}, {"indices": 2, "x": 0.8275165195428438, "y": 0.36120062880444687, "visibility": 1.0}, {"indices": 3, "x": 0.6324288143808756, "y": 0.28130302638815496, "visibility": 1.0}, {"indices": 4, "x": 0.5162412022802615, "y": 0.3499213451770799, "visibility": 1.0}, {"indices": 5, "x": 0.7418782993187376, "y": 0.4869729702755462, "visibility": 1.0}, {"indices": 6, "x": 0.5305062245161224, "y": 0.4237330621639561, "visibility": 1.0}, {"indices": 7, "x": 0.5881870477533699, "y": 0.402650037571595, "visibility": 1.0}, {"indices": 8, "x": 0.6539573123275769, "y": 0.4301727561921907, "visibility": 1.0}, {"indices": 9, "x": 0.687370012629524, "y": 0.6265016666458697, "visibility": 1.0}, {"indices": 10, "x": 0.4849049294199901, "y": 0.5282997594748919, "visibility": 1.0}, {"indices": 11, "x": 0.5528861990813304, "y": 0.5016616180617565, "visibility": 1.0}, {"indices": 12, "x": 0.6092948206307319, "y": 0.5219808556467095, "visibility": 1.0}, {"indices": 13, "x": 0.650498806816666, "y": 0.7323554275924266, "visibility": 1.0}, {"indices": 14, "x": 0.45941824133475206, "y": 0.6277319965634637, "visibility": 1.0}, {"indices": 15, "x": 0.5120353653457583, "y": 0.585627030859971, "visibility": 1.0}, {"indices": 16, "x": 0.5739611067998565, "y": 0.6023441741282306, "visibility": 1.0}, {"indices": 17, "x": 0.6234430896667177, "y": 0.8053804890426193, "visibility": 1.0}, {"indices": 18, "x": 0.4237711209179286, "y": 0.7340433247915016, "visibility": 1.0}, {"indices": 19, "x": 0.320532701840937, "y": 0.6986184468714963, "visibility": 1.0}, {"indices": 20, "x": 0.2353352609045589, "y": 0.6968347170741884, "visibility": 1.0}]}, {"pose": [{"indices": 0, "x": 0.0, "y": 0.0, "visibility": 0.0}, {"indices": 1, "x": 0.0, "y": 0.0, "visibility": 0.0}, {"indices": 2, "x": 0.0, "y": 0.0, "visibility": 0.0}, {"indices": 3, "x": 0.0, "y": 0.0, "visibility": 0.0}, {"indices": 4, "x": 0.0, "y": 0.0, "visibility": 0.0}, {"indices": 5, "x": 0.0, "y": 0.0, "visibility": 0.0}, {"indices": 6, "x": 0.0, "y": 0.0, "visibility": 0.0}, {"indices": 7, "x": 0.0, "y": 0.0, "visibility": 0.0}, {"indices": 8, "x": 0.0, "y": 0.0, "visibility": 0.0}, {"indices": 9, "x": 0.0, "y": 0.0, "visibility": 0.0}, {"indices": 10, "x": 0.0, "y": 0.0, "visibility": 0.0}, {"indices": 11, "x": 0.0, "y": 0.0, "visibility": 0.0}, {"indices": 12, "x": 0.0, "y": 0.0, "visibility": 0.0}, {"indices": 13, "x": 0.0, "y": 0.0, "visibility": 0.0}, {"indices": 14, "x": 0.0, "y": 0.0, "visibility": 0.0}, {"indices": 15, "x": 0.0, "y": 0.0, "visibility": 0.0}, {"indices": 16, "x": 0.0, "y": 0.0, "visibility": 0.0}, {"indices": 23, "x": 0.0, "y": 0.0, "visibility": 0.0}, {"indices": 24, "x": 0.0, "y": 0.0, "visibility": 0.0}], "left_hand": [{"indices": 0, "x": 0.0, "y": 0.0, "visibility": 0.0}, {"indices": 1, "x": 0.0, "y": 0.0, "visibility": 0.0}, {"indices": 2, "x": 0.0, "y": 0.0, "visibility": 0.0}, {"indices": 3, "x": 0.0, "y": 0.0, "visibility": 0.0}, {"indices": 4, "x": 0.0, "y": 0.0, "visibility": 0.0}, {"indices": 5, "x": 0.0, "y": 0.0, "visibility": 0.0}, {"indices": 6, "x": 0.0, "y": 0.0, "visibility": 0.0}, {"indices": 7, "x": 0.0, "y": 0.0, "visibility": 0.0}, {"indices": 8, "x": 0.0, "y": 0.0, "visibility": 0.0}, {"indices": 9, "x": 0.0, "y": 0.0, "visibility": 0.0}, {"indices": 10, "x": 0.0, "y": 0.0, "visibility": 0.0}, {"indices": 11, "x": 0.0, "y": 0.0, "visibility": 0.0}, {"indices": 12, "x": 0.0, "y": 0.0, "visibility": 0.0}, {"indices": 13, "x": 0.0, "y": 0.0, "visibility": 0.0}, {"indices": 14, "x": 0.0, "y": 0.0, "visibility": 0.0}, {"indices": 15, "x": 0.0, "y": 0.0, "visibility": 0.0}, {"indices": 16, "x": 0.0, "y": 0.0, "visibility": 0.0}, {"indices": 17, "x": 0.0, "y": 0.0, "visibility": 0.0}, {"indices": 18, "x": 0.0, "y": 0.0, "visibility": 0.0}, {"indices": 19, "x": 0.0, "y": 0.0, "visibility": 0.0}, {"indices": 20, "x": 0.0, "y": 0.0, "visibility": 0.0}], "right_hand": [{"indices": 0, "x": 0.0, "y": 0.0, "visibility": 0.0}, {"indices": 1, "x": 0.9629703750856772, "y": 0.4971675879305752, "visibility": 1.0}, {"indices": 2, "x": 0.825412122801008, "y": 0.35859704462810754, "visibility": 1.0}, {"indices": 3, "x": 0.6356889887816993, "y": 0.2822230059205481, "visibility": 1.0}, {"indices": 4, "x": 0.5170046039064611, "y": 0.3496088917360937, "visibility": 1.0}, {"indices": 5, "x": 0.7413596213464831, "y": 0.48917053540409866, "visibility": 1.0}, {"indices": 6, "x": 0.5331379882471168, "y": 0.4244314340415496, "visibility": 1.0}, {"indices": 7, "x": 0.5863413607842506, "y": 0.40503589427793435, "visibility": 1.0}, {"indices": 8, "x": 0.6519751591060309, "y": 0.4287433713050649, "visibility": 1.0}, {"indices": 9, "x": 0.6875709369316881, "y": 0.6242757922589677, "visibility": 1.0}, {"indices": 10, "x": 0.4844898659619022, "y": 0.5281527017439693, "visibility": 1.0}, {"indices": 11, "x": 0.5542764656884215, "y": 0.5052013101899541, "visibility": 1.0}, {"indices": 12, "x": 0.6099117552853225, "y": 0.5214877125336257, "visibility": 1.0}, {"indices": 13, "x": 0.648260100521718, "y": 0.7337771057232039, "visibility": 1.0}, {"indices": 14, "x": 0.45993392920914683, "y": 0.6286563355129969, "visibility": 1.0}, {"indices": 15, "x": 0.5129978049238186, "y": 0.5843504702085714, "visibility": 1.0}, {"indices": 16, "x": 0.5743094987279982, "y": 0.6021911000189668, "visibility": 1.0}, {"indices": 17, "x": 0.625612700778554, "y": 0.8074730226708736, "visibility": 1.0}, {"indices": 18, "x": 0.4253427986252231, "y": 0.7329564435516976, "visibility": 1.0}, {"indices": 19, "x": 0.3196790531612912, "y": 0.6998376437883368, "visibility": 1.0}, {"indices": 20, "x": 0.23799573040240493, "y": 0.6970301966021509, "visibility": 1.0}]}, {"pose": [{"indices": 0, "x": 0.0, "y": 0.0, "visibility": 0.0}, {"indices": 1, "x": 0.0, "y": 0.0, "visibility": 0.0}, {"indices": 2, "x": 0.0, "y": 0.0, "visibility": 0.0}, {"indices": 3, "x": 0.0, "y": 0.0, "visibility": 0.0}, {"indices": 4, "x": 0.0, "y": 0.0, "visibility": 0.0}, {"indices": 5, "x": 0.0, "y": 0.0, "visibility": 0.0}, {"indices": 6, "x": 0.0, "y": 0.0, "visibility": 0.0}, {"indices": 7, "x": 0.0, "y": 0.0, "visibility": 0.0}, {"indices": 8, "x": 0.0, "y": 0.0, "visibility": 0.0}, {"indices": 9, "x": 0.0, "y": 0.0, "visibility": 0.0}, {"indices": 10, "x": 0.0, "y": 0.0, "visibility": 0.0}, {"indices": 11, "x": 0.0, "y": 0.0, "visibility": 0.0}, {"indices": 12, "x": 0.0, "y": 0.0, "visibility": 0.0}, {"indices": 13, "x": 0.0, "y": 0.0, "visibility": 0.0}, {"indices": 14, "x": 0.0, "y": 0.0, "visibility": 0.0}, {"indices": 15, "x": 0.0, "y": 0.0, "visibility": 0.0}, {"indices": 16, "x": 0.0, "y": 0.0, "visibility": 0.0}, {"indices": 23, "x": 0.0, "y": 0.0, "visibility": 0.0}, {"indices": 24, "x": 0.0, "y": 0.0, "visibility": 0.0}], "left_hand": [{"indices": 0, "x": 0.0, "y": 0.0, "visibility": 0.0}, {"indices": 1, "x": 0.0, "y": 0.0, "visibility": 0.0}, {"indices": 2, "x": 0.0, "y": 0.0, "visibility": 0.0}, {"indices": 3, "x": 0.0, "y": 0.0, "visibility": 0.0}, {"indices": 4, "x": 0.0, "y": 0.0, "visibility": 0.0}, {"indices": 5, "x": 0.0, "y": 0.0, "visibility": 0.0}, {"indices": 6, "x": 0.0, "y": 0.0, "visibility": 0.0}, {"indices": 7, "x": 0.0, "y": 0.0, "visibility": 0.0}, {"indices": 8, "x": 0.0, "y": 0.0, "visibility": 0.0}, {"indices": 9, "x": 0.0, "y": 0.0, "visibility": 0.0}, {"indices": 10, "x": 0.0, "y": 0.0, "visibility": 0.0}, {"indices": 11, "x": 0.0, "y": 0.0, "visibility": 0.0}, {"indices": 12, "x": 0.0, "y": 0.0, "visibility": 0.0}, {"indices": 13, "x": 0.0, "y": 0.0, "visibility": 0.0}, {"indices": 14, "x": 0.0, "y": 0.0, "visibility": 0.0}, {"indices": 15, "x": 0.0, "y": 0.0, "visibility": 0.0}, {"indices": 16, "x": 0.0, "y": 0.0, "visibility": 0.0}, {"indices": 17, "x": 0.0, "y": 0.0, "visibility": 0.0}, {"indices": 18, "x": 0.0, "y": 0.0, "visibility": 0.0}, {"indices": 19, "x": 0.0, "y": 0.0, "visibility": 0.0}, {"indices": 20, "x": 0.0, "y": 0.0, "visibility": 0.0}], "right_hand": [{"indices": 0, "x": 0.0, "y": 0.0, "visibility": 0.0}, {"indices": 1, "x": 0.9593347144555686, "y": 0.49998604131827346, "visibility": 1.0}, {"indices": 2, "x": 0.826624853493531, "y": 0.3606635278013431, "visibility": 1.0}, {"indices": 3, "x": 0.6323790753311375, "y": 0.2831917308863315, "visibility": 1.0}, {"indices": 4, "x": 0.5174020290478619, "y": 0.3485321641036669, "visibility": 1.0}, {"indices": 5, "x": 0.7396614686980422, "y": 0.48748824972427496, "visibility": 1.0}, {"indices": 6, "x": 0.530123112616795, "y": 0.4239133180057823, "visibility": 1.0}, {"indices": 7, "x": 0.5849501455534335, "y": 0.4053052956390797, "visibility": 1.0}, {"indices": 8, "x": 0.6533842084711363, "y": 0.42918225271884625, "visibility": 1.0}, {"indices": 9, "x": 0.6860976901948537, "y": 0.6256238722897305, "visibility": 1.0}, {"indices": 10, "x": 0.485516262091667, "y": 0.5269858384647259, "visibility": 1.0}, {"indices": 11, "x": 0.5541647835007363, "y": 0.5016268641847224, "visibility": 1.0}, {"indices": 12, "x": 0.6101004482574942, "y": 0.5191882422563449, "visibility": 1.0}, {"indices": 13, "x": 0.6513468098139611, "y": 0.7350202797573422, "visibility": 1.0}, {"indices": 14, "x": 0.4623030230784118, "y": 0.6292214894406316, "visibility": 1.0}, {"indices": 15, "x": 0.5130405740395226, "y": 0.5849186740881864, "visibility": 1.0}, {"indices": 16, "x": 0.5736370444320531, "y": 0.602851283049286, "visibility": 1.0}, {"indices": 17, "x": 0.6255919275517967, "y": 0.8064410468956074, "visibility": 1.0}, {"indices": 18, "x": 0.42241651144808995, "y": 0.7335377191441509, "visibility": 1.0}, {"indices": 19, "x": 0.31932866911944546, "y": 0.6997589986594188, "visibility": 1.0}, {"indices": 20, "x": 0.23795435362105904, "y": 0.6957836769212321, "visibility": 1.0}]}]