[{"pose": [{"indices": 0, "x": 0.0, "y": 0.0, "visibility": 0.0}, {"indices": 1, "x": 0.0, "y": 0.0, "visibility": 0.0}, {"indices": 2, "x": 0.0, "y": 0.0, "visibility": 0.0}, {"indices": 3, "x": 0.0, "y": 0.0, "visibility": 0.0}, {"indices": 4, "x": 0.0, "y": 0.0, "visibility": 0.0}, {"indices": 5, "x": 0.0, "y": 0.0, "visibility": 0.0}, {"indices": 6, "x": 0.0, "y": 0.0, "visibility": 0.0}, {"indices": 7, "x": 0.0, "y": 0.0, "visibility": 0.0}, {"indices": 8, "x": 0.0, "y": 0.0, "visibility": 0.0}, {"indices": 9, "x": 0.0, "y": 0.0, "visibility": 0.0}, {"indices": 10, "x": 0.0, "y": 0.0, "visibility": 0.0}, {"indices": 11, "x": 0.0, "y": 0.0, "visibility": 0.0}, {"indices": 12, "x": 0.0, "y": 0.0, "visibility": 0.0}, {"indices": 13, "x": 0.0, "y": 0.0, "visibility": 0.0}, {"indices": 14, "x": 0.0, "y": 0.0, "visibility": 0.0}, {"indices": 15, "x": 0.0, "y": 0.0, "visibility": 0.0}, {"indices": 16, "x": 0.0, "y": 0.0, "visibility": 0.0}, {"indices": 23, "x": 0.0, "y": 0.0, "visibility": 0.0}, {"indices": 24, "x": 0.0, "y": 0.0, "visibility": 0.0}], "left_hand": [{"indices": 0, "x": 0.0, "y": 0.0, "visibility": 0.0}, {"indices": 1, "x": 0.0, "y": 0.0, "visibility": 0.0}, {"indices": 2, "x": 0.0, "y": 0.0, "visibility": 0.0}, {"indices": 3, "x": 0.0, "y": 0.0, "visibility": 0.0}, {"indices": 4, "x": 0.0, "y": 0.0, "visibility": 0.0}, {"indices": 5, "x": 0.0, "y": 0.0, "visibility": 0.0}, {"indices": 6, "x": 0.0, "y": 0.0, "visibility": 0.0}, {"indices": 7, "x": 0.0, "y": 0.0, "visibility": 0.0}, {"indices": 8, "x": 0.0, "y": 0.0, "visibility": 0.0}, {"indices": 9, "x": 0.0, "y": 0.0, "visibility": 0.0}, {"indices": 10, "x": 0.0, "y": 0.0, "visibility": 0.0}, {"indices": 11, "x": 0.0, "y": 0.0, "visibility": 0.0}, {"indices": 12, "x": 0.0, "y": 0.0, "visibility": 0.0}, {"indices": 13, "x": 0.0, "y": 0.0, "visibility": 0.0}, {"indices": 14, "x": 0.0, "y": 0.0, "visibility": 0.0}, {"indices": 15, "x": 0.0, "y": 0.0, "visibility": 0.0}, {"indices": 16, "x": 0.0, "y": 0.0, "visibility": 0.0}, {"indices": 17, "x": 0.0, "y": 0.0, "visibility": 0.0}, {"indices": 18, "x": 0.0, "y": 0.0, "visibility": 0.0}, {"indices": 19, "x": 0.0, "y": 0.0, "visibility": 0.0}, {"indices": 20, "x": 0.0, "y": 0.0, "visibility": 0.0}], "right_hand": [{"indices": 0, "x": 0.8152507128494149, "y": 0.5552803898335621, "visibility": 1.0}, {"indices": 1, "x": 0.7372436201807565, "y": 0.5541492586664198, "visibility": 1.0}, {"indices": 2, "x": 0.5979237086474849, "y": 0.5358527289339818, "visibility": 1.0}, {"indices": 3, "x": 0.4729852093502996, "y": 0.5056048337210405, "visibility": 1.0}, {"indices": 4, "x": 0.36825050016909083, "y": 0.48132534236723906, "visibility": 1.0}, {"indices": 5, "x": 0.5200602351560639, "y": 0.42890813719622284, "visibility": 1.0}, {"indices": 6, "x": 0.3407312496086532, "y": 0.4739374441717842, "visibility": 1.0}, {"indices": 7, "x": 0.25123840046081886, "y": 0.5179991508665872, "visibility": 1.0}, {"indices": 8, "x": 0.1951509567157464, "y": 0.529811032472507, "visibility": 1.0}, {"indices": 9, "x": 0.5313200993712818, "y": 0.44631793881867926, "visibility": 1.0}, {"indices": 10, "x": 0.43045555492628995, "y": 0.513849605597142, "visibility": 1.0}, {"indices": 11, "x": 0.4708972454471659, "y": 0.5620723262921602, "visibility": 1.0}, {"indices": 12, "x": 0.532622873691913, "y": 0.5791307444684655, "visibility": 1.0}, {"indices": 13, "x": 0.5474324253777187, "y": 0.47333577026968876, "visibility": 1.0}, {"indices": 14, "x": 0.4861876625617848, "y": 0.5388995664151538, "visibility": 1.0}, {"indices": 15, "x": 0.5453025520520793, "y": 0.5828297926657199, "visibility": 1.0}, {"indices": 16, "x": 0.6042148700428178, "y": 0.5881454712398533, "visibility": 1.0}, {"indices": 17, "x": 0.5597657317074336, "y": 0.4961996124620285, "visibility": 1.0}, {"indices": 18, "x": 0.5237982505368639, "y": 0.5492592044232175, "visibility": 1.0}, {"indices": 19, "x": 0.5638427818577819, "y": 0.5763566738069962, "visibility": 1.0}, {"indices": 20, "x": 0.6125142286740065, "y": 0.5739564420650586, "visibility": 1.0}]}, {"pose": [{"indices": 0, "x": 0.0, "y": 0.0, "visibility": 0.0}, {"indices": 1, "x": 0.0, "y": 0.0, "visibility": 0.0}, {"indices": 2, "x": 0.0, "y": 0.0, "visibility": 0.0}, {"indices": 3, "x": 0.0, "y": 0.0, "visibility": 0.0}, {"indices": 4, "x": 0.0, "y": 0.0, "visibility": 0.0}, {"indices": 5, "x": 0.0, "y": 0.0, "visibility": 0.0}, {"indices": 6, "x": 0.0, "y": 0.0, "visibility": 0.0}, {"indices": 7, "x": 0.0, "y": 0.0, "visibility": 0.0}, {"indices": 8, "x": 0.0, "y": 0.0, "visibility": 0.0}, {"indices": 9, "x": 0.0, "y": 0.0, "visibility": 0.0}, {"indices": 10, "x": 0.0, "y": 0.0, "visibility": 0.0}, {"indices": 11, "x": 0.0, "y": 0.0, "visibility": 0.0}, {"indices": 12, "x": 0.0, "y": 0.0, "visibility": 0.0}, {"indices": 13, "x": 0.0, "y": 0.0, "visibility": 0.0}, {"indices": 14, "x": 0.0, "y": 0.0, "visibility": 0.0}, {"indices": 15, "x": 0.0, "y": 0.0, "visibility": 0.0}, {"indices": 16, "x": 0.0, "y": 0.0, "visibility": 0.0}, {"indices": 23, "x": 0.0, "y": 0.0, "visibility": 0.0}, {"indices": 24, "x": 0.0, "y": 0.0, "visibility": 0.0}], "left_hand": [{"indices": 0, "x": 0.0, "y": 0.0, "visibility": 0.0}, {"indices": 1, "x": 0.0, "y": 0.0, "visibility": 0.0}, {"indices": 2, "x": 0.0, "y": 0.0, "visibility": 0.0}, {"indices": 3, "x": 0.0, "y": 0.0, "visibility": 0.0}, {"indices": 4, "x": 0.0, "y": 0.0, "visibility": 0.0}, {"indices": 5, "x": 0.0, "y": 0.0, "visibility": 0.0}, {"indices": 6, "x": 0.0, "y": 0.0, "visibility": 0.0}, {"indices": 7, "x": 0.0, "y": 0.0, "visibility": 0.0}, {"indices": 8, "x": 0.0, "y": 0.0, "visibility": 0.0}, {"indices": 9, "x": 0.0, "y": 0.0, "visibility": 0.0}, {"indices": 10, "x": 0.0, "y": 0.0, "visibility": 0.0}, {"indices": 11, "x": 0.0, "y": 0.0, "visibility": 0.0}, {"indices": 12, "x": 0.0, "y": 0.0, "visibility": 0.0}, {"indices": 13, "x": 0.0, "y": 0.0, "visibility": 0.0}, {"indices": 14, "x": 0.0, "y": 0.0, "visibility": 0.0}, {"indices": 15, "x": 0.0, "y": 0.0, "visibility": 0.0}, {"indices": 16, "x": 0.0, "y": 0.0, "visibility": 0.0}, {"indices": 17, "x": 0.0, "y": 0.0, "visibility": 0.0}, {"indices": 18, "x": 0.0, "y": 0.0, "visibility": 0.0}, {"indices": 19, "x": 0.0, "y": 0.0, "visibility": 0.0}, {"indices": 20, "x": 0.0, "y": 0.0, "visibility": 0.0}], "right_hand": [{"indices": 0, "x": 0.816129013825875, "y": 0.5544976498031112, "visibility": 1.0}, {"indices": 1, "x": 0.736280333056996, "y": 0.5573647359263959, "visibility": 1.0}, {"indices": 2, "x": 0.5999158790649972, "y": 0.5332106609507841, "visibility": 1.0}, {"indices": 3, "x": 0.4716225737515358, "y": 0.5030384461888187, "visibility": 1.0}, {"indices": 4, "x": 0.368351105795519, "y": 0.48465565606404926, "visibility": 1.0}, {"indices": 5, "x": 0.5217264454652164, "y": 0.4314858779046645, "visibility": 1.0}, {"indices": 6, "x": 0.3400123631783028, "y": 0.47551369448695713, "visibility": 1.0}, {"indices": 7, "x": 0.2506471186047994, "y": 0.5144660888589944, "visibility": 1.0}, {"indices": 8, "x": 0.19308618326687788, "y": 0.531598389992865, "visibility": 1.0}, {"indices": 9, "x": 0.5307740379306118, "y": 0.44717318017117047, "visibility": 1.0}, {"indices": 10, "x": 0.42936235351443186, "y": 0.5134421341718788, "visibility": 1.0}, {"indices": 11, "x": 0.47091019522886707, "y": 0.5621780159433036, "visibility": 1.0}, {"indices": 12, "x": 0.53056826511317, "y": 0.5789370526881433, "visibility": 1.0}, {"indices": 13, "x": 0.5460515715621097, "y": 0.47429771542677085, "visibility": 1.0}, {"indices": 14, "x": 0.4861402067273452, "y": 0.5403668551175931, "visibility": 1.0}, {"indices": 15, "x": 0.5471636084480928, "y": 0.5840736593805329, "visibility": 1.0}, {"indices": 16, "x": 0.6032842933144044, "y": 0.5857444430200398, "visibility": 1.0}, {"indices": 17, "x": 0.5610757360078249, "y": 0.4952154937606642, "visibility": 1.0}, {"indices": 18, "x": 0.5248848228888483, "y": 0.5511356968417788, "visibility": 1.0}, {"indices": 19, "x": 0.565406129912502, "y": 0.5768802444287434, "visibility": 1.0}, {"indices": 20, "x": 0.6126855296917645, "y": 0.5737831674073137, "visibility": 1.0}]}, {"pose": [{"indices": 0, "x": 0.0, "y": 0.0, "visibility": 0.0}, {"indices": 1, "x": 0.0, "y": 0.0, "visibility": 0.0}, {"indices": 2, "x": 0.0, "y": 0.0, "visibility": 0.0}, {"indices": 3, "x": 0.0, "y": 0.0, "visibility": 0.0}, {"indices": 4, "x": 0.0, "y": 0.0, "visibility": 0.0}, {"indices": 5, "x": 0.0, "y": 0.0, "visibility": 0.0}, {"indices": 6, "x": 0.0, "y": 0.0, "visibility": 0.0}, {"indices": 7, "x": 0.0, "y": 0.0, "visibility": 0.0}, {"indices": 8, "x": 0.0, "y": 0.0, "visibility": 0.0}, {"indices": 9, "x": 0.0, "y": 0.0, "visibility": 0.0}, {"indices": 10, "x": 0.0, "y": 0.0, "visibility": 0.0}, {"indices": 11, "x": 0.0, "y": 0.0, "visibility": 0.0}, {"indices": 12, "x": 0.0, "y": 0.0, "visibility": 0.0}, {"indices": 13, "x": 0.0, "y": 0.0, "visibility": 0.0}, {"indices": 14, "x": 0.0, "y": 0.0, "visibility": 0.0}, {"indices": 15, "x": 0.0, "y": 0.0, "visibility": 0.0}, {"indices": 16, "x": 0.0, "y": 0.0, "visibility": 0.0}, {"indices": 23, "x": 0.0, "y": 0.0, "visibility": 0.0}, {"indices": 24, "x": 0.0, "y": 0.0, "visibility": 0.0}], "left_hand": [{"indices": 0, "x": 0.0, "y": 0.0, "visibility": 0.0}, {"indices": 1, "x": 0.0, "y": 0.0, "visibility": 0.0}, {"indices": 2, "x": 0.0, "y": 0.0, "visibility": 0.0}, {"indices": 3, "x": 0.0, "y": 0.0, "visibility": 0.0}, {"indices": 4, "x": 0.0, "y": 0.0, "visibility": 0.0}, {"indices": 5, "x": 0.0, "y": 0.0, "visibility": 0.0}, {"indices": 6, "x": 0.0, "y": 0.0, "visibility": 0.0}, {"indices": 7, "x": 0.0, "y": 0.0, "visibility": 0.0}, {"indices": 8, "x": 0.0, "y": 0.0, "visibility": 0.0}, {"indices": 9, "x": 0.0, "y": 0.0, "visibility": 0.0}, {"indices": 10, "x": 0.0, "y": 0.0, "visibility": 0.0}, {"indices": 11, "x": 0.0, "y": 0.0, "visibility": 0.0}, {"indices": 12, "x": 0.0, "y": 0.0, "visibility": 0.0}, {"indices": 13, "x": 0.0, "y": 0.0, "visibility": 0.0}, {"indices": 14, "x": 0.0, "y": 0.0, "visibility": 0.0}, {"indices": 15, "x": 0.0, "y": 0.0, "visibility": 0.0}, {"indices": 16, "x": 0.0, "y": 0.0, "visibility": 0.0}, {"indices": 17, "x": 0.0, "y": 0.0, "visibility": 0.0}, {"indices": 18, "x": 0.0, "y": 0.0, "visibility": 0.0}, {"indices": 19, "x": 0.0, "y": 0.0, "visibility": 0.0}, {"indices": 20, "x": 0.0, "y": 0.0, "visibility": 0.0}], "right_hand": [{"indices": 0, "x": 0.8163768599940306, "y": 0.5529300017785562, "visibility": 1.0}, {"indices": 1, "x": 0.7392967936052866, "y": 0.5556093133284168, "visibility": 1.0}, {"indices": 2, "x": 0.5980811164239729, "y": 0.5347367073859438, "visibility": 1.0}, {"indices": 3, "x": 0.4709488817470858, "y": 0.5060319782806053, "visibility": 1.0}, {"indices": 4, "x": 0.3684321090825246, "y": 0.4824059495711752, "visibility": 1.0}, {"indices": 5, "x": 0.5199577414228275, "y": 0.42868525356827863, "visibility": 1.0}, {"indices": 6, "x": 0.3406008792075328, "y": 0.4772527098705045, "visibility": 1.0}, {"indices": 7, "x": 0.25040258576016317, "y": 0.5177170623577344, "visibility": 1.0}, {"indices": 8, "x": 0.19372737162870113, "y": 0.5302386959546725, "visibility": 1.0}, {"indices": 9, "x": 0.5309062124895912, "y": 0.44576964671840474, "visibility": 1.0}, {"indices": 10, "x": 0.42815831490356215, "y": 0.5149722668767324, "visibility": 1.0}, {"indices": 11, "x": 0.46823622164726086, "y": 0.5616017140026823, "visibility": 1.0}, {"indices": 12, "x": 0.5325942710317392, "y": 0.5787339347326523, "visibility": 1.0}, {"indices": 13, "x": 0.5470880627943014, "y": 0.47524839664533963, "visibility": 1.0}, {"indices": 14, "x": 0.48653390267591157, "y": 0.5384562306732776, "visibility": 1.0}, {"indices": 15, "x": 0.5474093990751944, "y": 0.5828278835200461, "visibility": 1.0}, {"indices": 16, "x": 0.6069296042759945, "y": 0.58783687133921, "visibility": 1.0}, {"indices": 17, "x": 0.5613763472815511, "y": 0.4941001347420775, "visibility": 1.0}, {"indices": 18, "x": 0.5242650040102764, "y": 0.549851934870101, "visibility": 1.0}, {"indices": 19, "x": 0.565323605930637, "y": 0.5780870177664404, "visibility": 1.0}, {"indices": 20, "x": 0.612734259115355, "y": 0.576178335769635, "visibility": 1.0}]}]