[{"pose": [{"indices": 0, "x": 0.0, "y": 0.0, "visibility": 0.0}, {"indices": 1, "x": 0.0, "y": 0.0, "visibility": 0.0}, {"indices": 2, "x": 0.0, "y": 0.0, "visibility": 0.0}, {"indices": 3, "x": 0.0, "y": 0.0, "visibility": 0.0}, {"indices": 4, "x": 0.0, "y": 0.0, "visibility": 0.0}, {"indices": 5, "x": 0.0, "y": 0.0, "visibility": 0.0}, {"indices": 6, "x": 0.0, "y": 0.0, "visibility": 0.0}, {"indices": 7, "x": 0.0, "y": 0.0, "visibility": 0.0}, {"indices": 8, "x": 0.0, "y": 0.0, "visibility": 0.0}, {"indices": 9, "x": 0.0, "y": 0.0, "visibility": 0.0}, {"indices": 10, "x": 0.0, "y": 0.0, "visibility": 0.0}, {"indices": 11, "x": 0.0, "y": 0.0, "visibility": 0.0}, {"indices": 12, "x": 0.0, "y": 0.0, "visibility": 0.0}, {"indices": 13, "x": 0.0, "y": 0.0, "visibility": 0.0}, {"indices": 14, "x": 0.0, "y": 0.0, "visibility": 0.0}, {"indices": 15, "x": 0.0, "y": 0.0, "visibility": 0.0}, {"indices": 16, "x": 0.0, "y": 0.0, "visibility": 0.0}, {"indices": 23, "x": 0.0, "y": 0.0, "visibility": 0.0}, {"indices": 24, "x": 0.0, "y": 0.0, "visibility": 0.0}], "left_hand": [{"indices": 0, "x": 0.06633767610386603, "y": 0.7575365569353465, "visibility": 1.0}, {"indices": 1, "x": 0.21366858522132934, "y": 0.7362669641747375, "visibility": 1.0}, {"indices": 2, "x": 0.30266223403503834, "y": 0.6429326194329152, "visibility": 1.0}, {"indices": 3, "x": 0.38202029057882986, "y": 0.5557592290424902, "visibility": 1.0}, {"indices": 4, "x": 0.4574977510607108, "y": 0.509467249998706, "visibility": 1.0}, {"indices": 5, "x": 0.2108279558897973, "y": 0.5003765184929096, "visibility": 1.0}, {"indices": 6, "x": 0.22894918204891634, "y": 0.36073815031278955, "visibility": 1.0}, {"indices": 7, "x": 0.22650432266111056, "y": 0.2711264085023785, "visibility": 1.0}, {"indices": 8, "x": 0.22455563189221184, "y": 0.20862254360190824, "visibility": 1.0}, {"indices": 9, "x": 0.12314714087273687, "y": 0.48567098976793177, "visibility": 1.0}, {"indices": 10, "x": 0.1802689465006429, "y": 0.4858912902446915, "visibility": 1.0}, {"indices": 11, "x": 0.18504950054746325, "y": 0.5430535508941443, "visibility": 1.0}, {"indices": 12, "x": 0.1693127376011721, "y": 0.5832862635211934, "visibility": 1.0}, {"indices": 13, "x": 0.05533334460416298, "y": 0.5138288069918531, "visibility": 1.0}, {"indices": 14, "x": 0.11443022534955101, "y": 0.5123589527837573, "visibility": 1.0}, {"indices": 15, "x": 0.12347101344691018, "y": 0.5581701435822957, "visibility": 1.0}, {"indices": 16, "x": 0.11364513435107186, "y": 0.5963107409133727, "visibility": 1.0}, {"indices": 17, "x": 0.0020361039738789983, "y": 0.5425012586889615, "visibility": 1.0}, {"indices": 18, "x": 0.05391966663848108, "y": 0.5422691481220153, "visibility": 1.0}, {"indices": 19, "x": 0.0625170370921349, "y": 0.5877588164816684, "visibility": 1.0}, {"indices": 20, "x": 0.05927676874100959, "y": 0.6195442380659888, "visibility": 1.0}], "right_hand": [{"indices": 0, "x": 0.8688188838190666, "y": 0.7395073774284964, "visibility": 1.0}, {"indices": 1, "x": 0.7181079333306218, "y": 0.7304184192840869, "visibility": 1.0}, {"indices": 2, "x": 0.6284271767334121, "y": 0.637735999707318, "visibility": 1.0}, {"indices": 3, "x": 0.5530834111744269, "y": 0.561879691833168, "visibility": 1.0}, {"indices": 4, "x": 0.48705958614524536, "y": 0.5029648967627833, "visibility": 1.0}, {"indices": 5, "x": 0.7160040841047477, "y": 0.5011917231120125, "visibility": 1.0}, {"indices": 6, "x": 0.7145225180752339, "y": 0.348673138081552, "visibility": 1.0}, {"indices": 7, "x": 0.7219108509909165, "y": 0.2532450458570772, "visibility": 1.0}, {"indices": 8, "x": 0.7301378262081331, "y": 0.1785235831995668, "visibility": 1.0}, {"indices": 9, "x": 0.8057216079749419, "y": 0.4727163797497581, "visibility": 1.0}, {"indices": 10, "x": 0.7643066059519191, "y": 0.4705984442933195, "visibility": 1.0}, {"indices": 11, "x": 0.7486156019321555, "y": 0.5317156490886914, "visibility": 1.0}, {"indices": 12, "x": 0.7608140405812656, "y": 0.5748069129339604, "visibility": 1.0}, {"indices": 13, "x": 0.8859920574104021, "y": 0.4910928534966619, "visibility": 1.0}, {"indices": 14, "x": 0.8254696565053773, "y": 0.4938120143668552, "visibility": 1.0}, {"indices": 15, "x": 0.8149424219985526, "y": 0.5396671402106779, "visibility": 1.0}, {"indices": 16, "x": 0.8343594405492075, "y": 0.5786062835868347, "visibility": 1.0}, {"indices": 17, "x": 0.9386018624895873, "y": 0.5099727857991796, "visibility": 1.0}, {"indices": 18, "x": 0.8884775218147412, "y": 0.5180595195711556, "visibility": 1.0}, {"indices": 19, "x": 0.8771790885655937, "y": 0.5609612829020598, "visibility": 1.0}, {"indices": 20, "x": 0.8890218172641717, "y": 0.5971026581447324, "visibility": 1.0}]}, {"pose": [{"indices": 0, "x": 0.0, "y": 0.0, "visibility": 0.0}, {"indices": 1, "x": 0.0, "y": 0.0, "visibility": 0.0}, {"indices": 2, "x": 0.0, "y": 0.0, "visibility": 0.0}, {"indices": 3, "x": 0.0, "y": 0.0, "visibility": 0.0}, {"indices": 4, "x": 0.0, "y": 0.0, "visibility": 0.0}, {"indices": 5, "x": 0.0, "y": 0.0, "visibility": 0.0}, {"indices": 6, "x": 0.0, "y": 0.0, "visibility": 0.0}, {"indices": 7, "x": 0.0, "y": 0.0, "visibility": 0.0}, {"indices": 8, "x": 0.0, "y": 0.0, "visibility": 0.0}, {"indices": 9, "x": 0.0, "y": 0.0, "visibility": 0.0}, {"indices": 10, "x": 0.0, "y": 0.0, "visibility": 0.0}, {"indices": 11, "x": 0.0, "y": 0.0, "visibility": 0.0}, {"indices": 12, "x": 0.0, "y": 0.0, "visibility": 0.0}, {"indices": 13, "x": 0.0, "y": 0.0, "visibility": 0.0}, {"indices": 14, "x": 0.0, "y": 0.0, "visibility": 0.0}, {"indices": 15, "x": 0.0, "y": 0.0, "visibility": 0.0}, {"indices": 16, "x": 0.0, "y": 0.0, "visibility": 0.0}, {"indices": 23, "x": 0.0, "y": 0.0, "visibility": 0.0}, {"indices": 24, "x": 0.0, "y": 0.0, "visibility": 0.0}], "left_hand": [{"indices": 0, "x": 0.06647253988372348, "y": 0.7585950856999141, "visibility": 1.0}, {"indices": 1, "x": 0.2113625950409784, "y": 0.7345187261195383, "visibility": 1.0}, {"indices": 2, "x": 0.299569187605259, "y": 0.643431382053761, "visibility": 1.0}, {"indices": 3, "x": 0.37904966326818706, "y": 0.5536369873228402, "visibility": 1.0}, {"indices": 4, "x": 0.4580124702113657, "y": 0.512120852414701, "visibility": 1.0}, {"indices": 5, "x": 0.21175332282053588, "y": 0.4974391025222755, "visibility": 1.0}, {"indices": 6, "x": 0.230377222997898, "y": 0.359863372228985, "visibility": 1.0}, {"indices": 7, "x": 0.22950541421237924, "y": 0.2717506695986748, "visibility": 1.0}, {"indices": 8, "x": 0.22435809162525333, "y": 0.20782385088217314, "visibility": 1.0}, {"indices": 9, "x": 0.1255576934505404, "y": 0.4849853013137778, "visibility": 1.0}, {"indices": 10, "x": 0.17867661091663395, "y": 0.48289184134725627, "visibility": 1.0}, {"indices": 11, "x": 0.18650653353107807, "y": 0.5407034334565648, "visibility": 1.0}, {"indices": 12, "x": 0.17021319202335228, "y": 0.5853865036518697, "visibility": 1.0}, {"indices": 13, "x": 0.05515358428661624, "y": 0.5100059679270861, "visibility": 1.0}, {"indices": 14, "x": 0.11167201204160924, "y": 0.5110252006853233, "visibility": 1.0}, {"indices": 15, "x": 0.12393117986668319, "y": 0.5592215796317874, "visibility": 1.0}, {"indices": 16, "x": 0.110951134504139, "y": 0.5976032116789588, "visibility": 1.0}, {"indices": 17, "x": 0.004384030622114916, "y": 0.5435517727903936, "visibility": 1.0}, {"indices": 18, "x": 0.05448434219586774, "y": 0.5433959736552788, "visibility": 1.0}, {"indices": 19, "x": 0.06327134728933727, "y": 0.5845742844168244, "visibility": 1.0}, {"indices": 20, "x": 0.059697200018763635, "y": 0.618245529200404, "visibility": 1.0}], "right_hand": [{"indices": 0, "x": 0.8695432483464937, "y": 0.7389694043371503, "visibility": 1.0}, {"indices": 1, "x": 0.7212329884386087, "y": 0.7275748985765444, "visibility": 1.0}, {"indices": 2, "x": 0.6298652657104082, "y": 0.638081911391164, "visibility": 1.0}, {"indices": 3, "x": 0.551389690007413, "y": 0.5616157709875006, "visibility": 1.0}, {"indices": 4, "x": 0.49067520943370807, "y": 0.5025516122006743, "visibility": 1.0}, {"indices": 5, "x": 0.7155042338711669, "y": 0.5002612052684934, "visibility": 1.0}, {"indices": 6, "x": 0.7163243491857549, "y": 0.34748122225055705, "visibility": 1.0}, {"indices": 7, "x": 0.7217458331979872, "y": 0.2537130767110727, "visibility": 1.0}, {"indices": 8, "x": 0.7317644150909912, "y": 0.17912748562072872, "visibility": 1.0}, {"indices": 9, "x": 0.806801804340856, "y": 0.4728343523656105, "visibility": 1.0}, {"indices": 10, "x": 0.764264295723147, "y": 0.47205572617456765, "visibility": 1.0}, {"indices": 11, "x": 0.7454807812246755, "y": 0.532202358559737, "visibility": 1.0}, {"indices": 12, "x": 0.7596390015382156, "y": 0.5746631013431077, "visibility": 1.0}, {"indices": 13, "x": 0.8834052065858538, "y": 0.4890775852091939, "visibility": 1.0}, {"indices": 14, "x": 0.8243915659040062, "y": 0.4943987248682781, "visibility": 1.0}, {"indices": 15, "x": 0.8172456436913872, "y": 0.5406116196204946, "visibility": 1.0}, {"indices": 16, "x": 0.8321022255195307, "y": 0.5790230588645283, "visibility": 1.0}, {"indices": 17, "x": 0.9403933460786666, "y": 0.5128544369557249, "visibility": 1.0}, {"indices": 18, "x": 0.8866909278196387, "y": 0.5179188922190909, "visibility": 1.0}, {"indices": 19, "x": 0.876345230158552, "y": 0.5607158953319189, "visibility": 1.0}, {"indices": 20, "x": 0.8903249604625515, "y": 0.5937417296777274, "visibility": 1.0}]}, {"pose": [{"indices": 0, "x": 0.0, "y": 0.0, "visibility": 0.0}, {"indices": 1, "x": 0.0, "y": 0.0, "visibility": 0.0}, {"indices": 2, "x": 0.0, "y": 0.0, "visibility": 0.0}, {"indices": 3, "x": 0.0, "y": 0.0, "visibility": 0.0}, {"indices": 4, "x": 0.0, "y": 0.0, "visibility": 0.0}, {"indices": 5, "x": 0.0, "y": 0.0, "visibility": 0.0}, {"indices": 6, "x": 0.0, "y": 0.0, "visibility": 0.0}, {"indices": 7, "x": 0.0, "y": 0.0, "visibility": 0.0}, {"indices": 8, "x": 0.0, "y": 0.0, "visibility": 0.0}, {"indices": 9, "x": 0.0, "y": 0.0, "visibility": 0.0}, {"indices": 10, "x": 0.0, "y": 0.0, "visibility": 0.0}, {"indices": 11, "x": 0.0, "y": 0.0, "visibility": 0.0}, {"indices": 12, "x": 0.0, "y": 0.0, "visibility": 0.0}, {"indices": 13, "x": 0.0, "y": 0.0, "visibility": 0.0}, {"indices": 14, "x": 0.0, "y": 0.0, "visibility": 0.0}, {"indices": 15, "x": 0.0, "y": 0.0, "visibility": 0.0}, {"indices": 16, "x": 0.0, "y": 0.0, "visibility": 0.0}, {"indices": 23, "x": 0.0, "y": 0.0, "visibility": 0.0}, {"indices": 24, "x": 0.0, "y": 0.0, "visibility": 0.0}], "left_hand": [{"indices": 0, "x": 0.06628086273944783, "y": 0.7557160446443387, "visibility": 1.0}, {"indices": 1, "x": 0.21234652050269362, "y": 0.7335783744072119, "visibility": 1.0}, {"indices": 2, "x": 0.3004082302135662, "y": 0.643882123698596, "visibility": 1.0}, {"indices": 3, "x": 0.38110395343080233, "y": 0.5545712243837964, "visibility": 1.0}, {"indices": 4, "x": 0.4587114928575704, "y": 0.5093766443588335, "visibility": 1.0}, {"indices": 5, "x": 0.21172902871061516, "y": 0.5002550613235204, "visibility": 1.0}, {"indices": 6, "x": 0.22826500333644748, "y": 0.35977467481385766, "visibility": 1.0}, {"indices": 7, "x": 0.22886833469603277, "y": 0.2739893884651092, "visibility": 1.0}, {"indices": 8, "x": 0.22203165838970218, "y": 0.20989394990743762, "visibility": 1.0}, {"indices": 9, "x": 0.1253055739477378, "y": 0.4853424264863641, "visibility": 1.0}, {"indices": 10, "x": 0.17823287634410934, "y": 0.4824093030004923, "visibility": 1.0}, {"indices": 11, "x": 0.18687696044532512, "y": 0.5421236165075747, "visibility": 1.0}, {"indices": 12, "x": 0.17144232729625994, "y": 0.5827083957269911, "visibility": 1.0}, {"indices": 13, "x": 0.057663629372794255, "y": 0.5108274345890573, "visibility": 1.0}, {"indices": 14, "x": 0.11520459061059692, "y": 0.5110128551598655, "visibility": 1.0}, {"indices": 15, "x": 0.12025291128985106, "y": 0.5595748960233161, "visibility": 1.0}, {"indices": 16, "x": 0.11299560460623045, "y": 0.5970060766198189, "visibility": 1.0}, {"indices": 17, "x": 0.0004997709668909426, "y": 0.5437044328914835, "visibility": 1.0}, {"indices": 18, "x": 0.0537712586250762, "y": 0.5442177475748535, "visibility": 1.0}, {"indices": 19, "x": 0.06437744985495532, "y": 0.5847949846699997, "visibility": 1.0}, {"indices": 20, "x": 0.062092966710162206, "y": 0.6196268530091386, "visibility": 1.0}], "right_hand": [{"indices": 0, "x": 0.8665255881427913, "y": 0.7400351738601535, "visibility": 1.0}, {"indices": 1, "x": 0.7193610127960136, "y": 0.7278464390942707, "visibility": 1.0}, {"indices": 2, "x": 0.6302292557735796, "y": 0.6404813271421528, "visibility": 1.0}, {"indices": 3, "x": 0.5509525658498574, "y": 0.562943717945951, "visibility": 1.0}, {"indices": 4, "x": 0.490370356704993, "y": 0.5031142060647289, "visibility": 1.0}, {"indices": 5, "x": 0.715720093979543, "y": 0.5011248243577706, "visibility": 1.0}, {"indices": 6, "x": 0.7183170332038626, "y": 0.3470677889594788, "visibility": 1.0}, {"indices": 7, "x": 0.7221023084199185, "y": 0.25101569173716815, "visibility": 1.0}, {"indices": 8, "x": 0.7300117285038918, "y": 0.18046661065512376, "visibility": 1.0}, {"indices": 9, "x": 0.8094524913751263, "y": 0.4735083609349068, "visibility": 1.0}, {"indices": 10, "x": 0.7652557111801942, "y": 0.47214583584428205, "visibility": 1.0}, {"indices": 11, "x": 0.7492838488724891, "y": 0.5297290810643697, "visibility": 1.0}, {"indices": 12, "x": 0.7627100826199404, "y": 0.5746205452067654, "visibility": 1.0}, {"indices": 13, "x": 0.8836762065153042, "y": 0.4911681260830757, "visibility": 1.0}, {"indices": 14, "x": 0.8261937787270255, "y": 0.49427612472660454, "visibility": 1.0}, {"indices": 15, "x": 0.8173224644221446, "y": 0.540483891950121, "visibility": 1.0}, {"indices": 16, "x": 0.8337176154617317, "y": 0.5815646643536921, "visibility": 1.0}, {"indices": 17, "x": 0.9395392243301771, "y": 0.509756368252317, "visibility": 1.0}, {"indices": 18, "x": 0.8888658934213696, "y": 0.5169116184827284, "visibility": 1.0}, {"indices": 19, "x": 0.8755667843350929, "y": 0.5624073397233107, "visibility": 1.0}, {"indices": 20, "x": 0.8887599648329083, "y": 0.5961226530562165, "visibility": 1.0}]}]